interspace.py
interspace-0.0.10.dist-info/LICENSE
interspace-0.0.10.dist-info/METADATA
interspace-0.0.10.dist-info/WHEEL
interspace-0.0.10.dist-info/top_level.txt
interspace-0.0.10.dist-info/RECORD
