Metadata-Version: 2.1
Name: interspace
Version: 0.0.10
Summary: Interspace gives us different type distances between two vectors.
Home-page: https://github.com/rehanguha/interspace
Author: Rehan Guha
Author-email: rehanguha29@gmail.com
License: mit
Keywords: distance,ml,machine learning,maths,vectors,space
Platform: UNKNOWN
Classifier: Operating System :: OS Independent
Classifier: License :: OSI Approved :: MIT License
Classifier: Natural Language :: English
Classifier: Programming Language :: Python
Classifier: Topic :: Software Development :: Libraries :: Python Modules
Classifier: Topic :: Scientific/Engineering
Classifier: Intended Audience :: Developers
Requires-Python: >=2.7
Requires-Dist: numpy
